pistar_echo_agent/__init__.py
pistar_echo_agent/__main__.py
pistar_echo_agent/resources/__init__.py
pistar_echo_agent/resources/loggers.py
pistar_echo_agent/services/__init__.py
pistar_echo_agent/services/echotest/__init__.py
pistar_echo_agent/services/echotest/agent.py
pistar_echo_agent/services/echotest/base.py
pistar_echo_agent/utilities/__init__.py
pistar_echo_agent/utilities/argument_parser/__init__.py
pistar_echo_agent/utilities/argument_parser/argument_parser.py
pistar_echo_agent/utilities/configuration/__init__.py
pistar_echo_agent/utilities/configuration/configuration.py
pistar_echo_agent/utilities/configuration/server_configuration.py
pistar_echo_agent/utilities/constants/__init__.py
pistar_echo_agent/utilities/constants/api_document.py
pistar_echo_agent/utilities/constants/encode.py
pistar_echo_agent/utilities/constants/file.py
pistar_echo_agent/utilities/constants/file_mode.py
pistar_echo_agent/utilities/constants/pistar_logging.py
pistar_echo_agent/utilities/constants/report.py
pistar_echo_agent/utilities/constants/response.py
pistar_echo_agent/utilities/constants/testcase.py
pistar_echo_agent/utilities/exceptions/__init__.py
pistar_echo_agent/utilities/exceptions/common.py
pistar_echo_agent/utilities/exceptions/webserver.py
pistar_echo_agent/utilities/logger/__init__.py
pistar_echo_agent/utilities/logger/logger.py
pistar_echo_agent/utilities/server/__init__.py
pistar_echo_agent/utilities/server/check_arguments.py
pistar_echo_agent/utilities/server/get_arguments.py
pistar_echo_agent/utilities/server/handlers.py
pistar_echo_agent/utilities/server/server.py
pistar_echo_agent/utilities/testcase/__init__.py
pistar_echo_agent/utilities/testcase/compose_report.py
pistar_echo_agent/utilities/testsuite/__init__.py
pistar_echo_agent/utilities/testsuite/directory.py
pistar_echo_agent/utilities/testsuite/factory_testsuite.py
pistar_echo_agent/utilities/util/__init__.py
pistar_echo_agent/utilities/util/encode_util.py
pistar_echo_agent-1.0.8.dist-info/LICENSE
pistar_echo_agent-1.0.8.dist-info/METADATA
pistar_echo_agent-1.0.8.dist-info/WHEEL
pistar_echo_agent-1.0.8.dist-info/entry_points.txt
pistar_echo_agent-1.0.8.dist-info/top_level.txt
pistar_echo_agent-1.0.8.dist-info/RECORD
