Metadata-Version: 2.1
Name: pistar-echo-agent
Version: 1.0.8
Summary: pistar echo agent: support Huawei CloudTest execute test case
License: MIT
Keywords: test
Platform: linux
Platform: win32
Classifier: Development Status :: 6 - Mature
Classifier: Intended Audience :: Developers
Classifier: License :: OSI Approved :: MIT License
Classifier: Operating System :: Microsoft :: Windows
Classifier: Operating System :: POSIX
Classifier: Programming Language :: Python :: 3
Classifier: Programming Language :: Python :: 3 :: Only
Classifier: Programming Language :: Python :: 3.6
Classifier: Programming Language :: Python :: 3.7
Classifier: Programming Language :: Python :: 3.8
Classifier: Programming Language :: Python :: 3.9
Classifier: Topic :: Software Development :: Testing
Classifier: Topic :: Software Development :: Libraries
Requires-Python: >=3.6
License-File: LICENSE
Requires-Dist: colorlog (==6.7.0)
Requires-Dist: PyYAML (==6.0)
Requires-Dist: tornado (==6.2)
Requires-Dist: astunparse (==1.6.3)
Requires-Dist: colorama (==0.4.6)
